vtt/__init__.py
vt_timetable-0.2.6.dist-info/LICENSE
vt_timetable-0.2.6.dist-info/METADATA
vt_timetable-0.2.6.dist-info/WHEEL
vt_timetable-0.2.6.dist-info/top_level.txt
vt_timetable-0.2.6.dist-info/RECORD
