Metadata-Version: 2.1
Name: vt-timetable
Version: 0.2.6
Summary: A python module for scraping the Virginia Tech Timetable of Classes.
Home-page: https://github.com/dipernalz/vt-timetable
Author: Leo DiPerna
Author-email: dipernalz@vt.edu
License: UNKNOWN
Project-URL: Documentation, https://leodiperna.com/projects/vt-timetable/documentation
Project-URL: Issues, https://github.com/dipernalz/vt-timetable/issues
Platform: UNKNOWN
Classifier: Programming Language :: Python :: 3
Classifier: License :: OSI Approved :: MIT License
Classifier: Operating System :: OS Independent
Requires-Python: >=3.6
License-File: LICENSE
Requires-Dist: lxml
Requires-Dist: requests
Requires-Dist: pandas
